jsengine/__init__.py
jsengine/abstract.py
jsengine/chakra.py
jsengine/chakra_win.py
jsengine/detect.py
jsengine/exceptions.py
jsengine/external.py
jsengine/internal.py
jsengine/util.py
jsengine/v8.py
jsengine-1.0.7.post1.dist-info/LICENSE
jsengine-1.0.7.post1.dist-info/METADATA
jsengine-1.0.7.post1.dist-info/WHEEL
jsengine-1.0.7.post1.dist-info/top_level.txt
jsengine-1.0.7.post1.dist-info/zip-safe
jsengine-1.0.7.post1.dist-info/RECORD
