Metadata-Version: 2.1
Name: jsengine
Version: 1.0.7.post1
Summary: JSEngine is a simple wrapper of Javascript engines.
Home-page: https://github.com/SeaHOH/jsengine
Author: SeaHOH
Author-email: seahoh@gmail.com
License: MIT
Keywords: javascript js engine node chakra quickjs execjs
Platform: any
Classifier: Development Status :: 5 - Production/Stable
Classifier: Intended Audience :: Developers
Classifier: License :: OSI Approved :: MIT License
Classifier: Operating System :: OS Independent
Classifier: Programming Language :: Python
Classifier: Programming Language :: Python :: 2
Classifier: Programming Language :: Python :: 3
Classifier: Programming Language :: JavaScript
Classifier: Topic :: Software Development :: Interpreters
Classifier: Topic :: Utilities
Requires-Python: >=2.7
License-File: LICENSE
